basictypes
besseltools
catana
decomposition
io
