Metadata-Version: 1.0
Name: catana
Version: 2.0.0b4
Summary: A library for Spherical Fourier Bessel (SFB) Decomposition
Home-page: https://github.com/michaelbuehlmann/CatAna
Author: Michael Buehlmann
Author-email: michael.buehlmann@oca.eu
License: GPLv2
Keywords: SFB spherical Fourier Bessel transformation decomposition cosmology
Platform: UNKNOWN
